dbt/__init__.py
dbt/adapters/yellowbrick/__init__.py
dbt/adapters/yellowbrick/__version__.py
dbt/adapters/yellowbrick/connections.py
dbt/adapters/yellowbrick/impl.py
dbt/adapters/yellowbrick/relation.py
dbt/include/__init__.py
dbt/include/yellowbrick/__init__.py
dbt/include/yellowbrick/dbt_project.yml
dbt/include/yellowbrick/macros/adapters.sql
dbt/include/yellowbrick/macros/catalog.sql
dbt/include/yellowbrick/macros/materializations/cluster.sql
dbt/include/yellowbrick/macros/materializations/distribute.sql
dbt/include/yellowbrick/macros/materializations/snapshot_merge.sql
dbt/include/yellowbrick/macros/materializations/sort.sql
dbt/include/yellowbrick/macros/utils/hash.sql
dbt_yellowbrick-1.7.1.dist-info/LICENSE
dbt_yellowbrick-1.7.1.dist-info/METADATA
dbt_yellowbrick-1.7.1.dist-info/WHEEL
dbt_yellowbrick-1.7.1.dist-info/top_level.txt
dbt_yellowbrick-1.7.1.dist-info/RECORD
