Metadata-Version: 2.1
Name: dbt_yellowbrick
Version: 1.7.1
Summary: The Yellowbrick adapter plugin for dbt (data build tool)
Home-page: https://github.com/InfoCapital-AU/dbt-yellowbrick.git
Author: David Antelmi
Author-email: david.antelmi@infocapital.com.au
Classifier: Development Status :: 2 - Pre-Alpha
Classifier: License :: OSI Approved :: Apache Software License
Classifier: Operating System :: Microsoft :: Windows
Classifier: Operating System :: MacOS :: MacOS X
Classifier: Operating System :: POSIX :: Linux
Classifier: Programming Language :: Python :: 3.8
Classifier: Programming Language :: Python :: 3.9
Classifier: Programming Language :: Python :: 3.10
Classifier: Programming Language :: Python :: 3.11
Requires-Python: >=3.8
License-File: LICENSE
Requires-Dist: dbt-core ~=1.7.1
Requires-Dist: dbt-postgres ~=1.7.1
Requires-Dist: psycopg2-binary ~=2.8
